ipydex/__init__.py
ipydex/cli.py
ipydex/core.py
ipydex/displaytools.py
ipydex/release.py
ipydex/utils.py
ipydex-0.20.0.dist-info/licenses/LICENSE
ipydex-0.20.0.dist-info/METADATA
ipydex-0.20.0.dist-info/WHEEL
ipydex-0.20.0.dist-info/entry_points.txt
ipydex-0.20.0.dist-info/top_level.txt
ipydex-0.20.0.dist-info/RECORD
