Metadata-Version: 2.4
Name: ipydex
Version: 0.20.0
Summary: IPython based debugging and exploring tool
Author-email: Carsten Knoll <firstname.lastname@posteo.de>
License-Expression: GPL-3.0-or-later
Project-URL: Homepage, http://github.com/cknoll/ipydex
Classifier: Development Status :: 4 - Beta
Classifier: Intended Audience :: Developers
Classifier: Programming Language :: Python :: 3
Requires-Python: >=3.8
License-File: LICENSE
Requires-Dist: ipython>=9.0.0
Requires-Dist: pexpect
Requires-Dist: pickleshare
Requires-Dist: stack_data
Requires-Dist: colorama
Dynamic: license-file
